certbot_dns_ngenix/__init__.py
certbot_dns_ngenix/dns_ngenix.py
certbot_dns_ngenix/ngenix_api.py
certbot_dns_ngenix-0.0.2.dist-info/LICENSE.txt
certbot_dns_ngenix-0.0.2.dist-info/METADATA
certbot_dns_ngenix-0.0.2.dist-info/WHEEL
certbot_dns_ngenix-0.0.2.dist-info/entry_points.txt
certbot_dns_ngenix-0.0.2.dist-info/top_level.txt
certbot_dns_ngenix-0.0.2.dist-info/RECORD
