Metadata-Version: 2.1
Name: certbot-dns-ngenix
Version: 0.0.2
Summary: NGENIX DNS Authenticator plugin for Certbot
Home-page: https://github.com/maniack/certbot-dns-ngenix
Author: Igor Lazarev
Author-email: i.a.lazarev@gmail.com
License: MIT License
Platform: UNKNOWN
Classifier: Development Status :: 3 - Alpha
Classifier: Environment :: Plugins
Classifier: Intended Audience :: System Administrators
Classifier: License :: OSI Approved :: MIT License
Classifier: Operating System :: POSIX :: Linux
Classifier: Programming Language :: Python
Classifier: Programming Language :: Python :: 3
Classifier: Programming Language :: Python :: 3.4
Classifier: Programming Language :: Python :: 3.5
Classifier: Programming Language :: Python :: 3.6
Classifier: Programming Language :: Python :: 3.7
Classifier: Topic :: Internet :: WWW/HTTP
Classifier: Topic :: Security
Classifier: Topic :: System :: Installation/Setup
Classifier: Topic :: System :: Networking
Classifier: Topic :: System :: Systems Administration
Classifier: Topic :: Utilities
Requires-Python: >=3, !=3.0.*, !=3.1.*, !=3.2.*, !=3.3.*
License-File: LICENSE.txt
Requires-Dist: acme (>=0.29.0)
Requires-Dist: certbot (>=0.34.0)
Requires-Dist: setuptools
Requires-Dist: requests
